{
  "kind": "collectionType",
  "collectionName": "news",
  "info": {
    "singularName": "new",
    "pluralName": "news",
    "displayName": "new",
    "description": ""
  },
  "options": {
    "draftAndPublish": true
  },
  "pluginOptions": {},
  "attributes": {
    "Title": {
      "type": "string"
    },
    "Message": {
      "type": "text"
    },
    "Image": {
      "type": "media",
      "multiple": true,
      "required": false,
      "allowedTypes": [
        "images",
        "files",
        "videos",
        "audios"
      ]
    },
    "Cta_link": {
      "type": "string"
    }
  }
}
